SupOpNumTools/__init__.py
SupOpNumTools/essai_TD10.py
SupOpNumTools/physics_demo_systems_PHOTO.py
SupOpNumTools/physics_demo_systems_ali.py
SupOpNumTools/requirements.txt
SupOpNumTools/test.py
SupOpNumTools/__pycache__/__init__.cpython-39.pyc
SupOpNumTools/camera/__init__.py
SupOpNumTools/camera/camera.py
SupOpNumTools/camera/cameraBasler.py
SupOpNumTools/camera/cameraIDS.py
SupOpNumTools/camera/cameraIDSdisplay.py
SupOpNumTools/camera/cameraIDSdisplayQt6.py
SupOpNumTools/camera/__pycache__/__init__.cpython-311.pyc
SupOpNumTools/camera/__pycache__/__init__.cpython-39.pyc
SupOpNumTools/camera/__pycache__/camera.cpython-311.pyc
SupOpNumTools/camera/__pycache__/camera.cpython-39.pyc
SupOpNumTools/camera/__pycache__/cameraBasler.cpython-311.pyc
SupOpNumTools/camera/__pycache__/cameraIDS.cpython-311.pyc
SupOpNumTools/camera/__pycache__/cameraIDS.cpython-39.pyc
SupOpNumTools/camera/__pycache__/cameraIDSdisplay.cpython-311.pyc
SupOpNumTools/camera/__pycache__/cameraIDSdisplayQt6.cpython-311.pyc
SupOpNumTools/camera/__pycache__/cameraIDSdisplayQt6.cpython-39.pyc
SupOpNumTools/drivers/__init__.py
SupOpNumTools/drivers/piezoNucleo.py
SupOpNumTools/drivers/__pycache__/__init__.cpython-311.pyc
SupOpNumTools/drivers/__pycache__/piezoNucleo.cpython-311.pyc
SupOpNumTools/elecmodel/__init__.py
SupOpNumTools/elecmodel/photodetection.py
SupOpNumTools/elecmodel/__pycache__/__init__.cpython-311.pyc
SupOpNumTools/elecmodel/__pycache__/__init__.cpython-39.pyc
SupOpNumTools/elecmodel/__pycache__/elec_modeling_photodetection.cpython-39.pyc
SupOpNumTools/elecmodel/__pycache__/photodetection.cpython-311.pyc
SupOpNumTools/elecmodel/__pycache__/photodetection.cpython-39.pyc
SupOpNumTools/math_phys_methods/__init__.py
SupOpNumTools/math_phys_methods/math_phys_methods.py
SupOpNumTools/math_phys_methods/__pycache__/M2DFilesDatabase.cpython-37.pyc
SupOpNumTools/math_phys_methods/__pycache__/M2DFilesDatabase.cpython-38.pyc
SupOpNumTools/math_phys_methods/__pycache__/__init__.cpython-311.pyc
SupOpNumTools-1.0.0.dist-info/LICENCE
SupOpNumTools-1.0.0.dist-info/METADATA
SupOpNumTools-1.0.0.dist-info/WHEEL
SupOpNumTools-1.0.0.dist-info/entry_points.txt
SupOpNumTools-1.0.0.dist-info/top_level.txt
SupOpNumTools-1.0.0.dist-info/RECORD
